{
  "metadata": {
    "h1": "Planning a Party? See the OG Catering Menu & Prices 2025! 🥳",
    "description": "Be the hero of your next event with the Olive Garden Catering Menu! 🥳 See every party-sized pan and combo with prices for 2025. Plan your feast now! 👇",
    "coreKeyword": "Olive Garden Catering Menu",
    "author": {
      "name": "The Olive Garden Menu Guide Team",
      "email": "contact@olivegardenmenuguide.com"
    },
    "datePublished": "2025-08-30"
  },
  "contentBlocks": [
    {
      "type": "richText",
      "data": {
        "htmlContent": "<p>Wanna be the absolute HERO of your next party or family gathering? Easy. Just order from the Olive Garden catering menu. 😎 You get giant pans of all your favorite Italian dishes, plus their famous salad and those heavenly breadsticks. It's the easiest way to feed a crowd and make everyone happy. Let's check out the options! 🎉</p>"
      }
    },
    {
      "type": "dataTable",
      "data": {
        "title": "Olive Garden Catering Menu & Prices (September 2025)",
        "categories": {
          "CATERING": {
            "description": "Bring the taste of Olive Garden to your next event with our convenient and delicious catering pans. Everyone will thank you! 🙌",
            "recommended": "Lasagna Classico (Serves up to 12)",
            "items": [
              {
                "name": "Chicken Alfredo (Serves 4 – 6)",
                "calories": "6,050",
                "price": "66.99",
                "image_url": "/static/image/upload/Chicken-Alfredo-Serves-4-6-1.webp"
              },
              {
                "name": "Chicken Parmigiana (Serves 4 – 6)",
                "calories": "4,790",
                "price": "61.99",
                "image_url": "/static/image/upload/Chicken-Parmigiana-Serves-4-6-1.webp"
              },
              {
                "name": "Fettuccine Alfredo (Serves 4 – 6)",
                "calories": "5,010",
                "price": "50.99",
                "image_url": "/static/image/upload/Fettuccine-Alfredo-Serves-4-6-1.webp"
              },
              {
                "name": "Shrimp Alfredo (Serves 4 – 6)",
                "calories": "5,680",
                "price": "72.29",
                "image_url": "/static/image/upload/Shrimp-Alfredo-Serves-4-6-1.webp"
              },
              {
                "name": "Five Cheese Ziti al Forno (Serves 4 – 6)",
                "calories": "4,680",
                "price": "52.49",
                "image_url": "/static/image/upload/Five-Cheese-Ziti-al-Forno-Serves-4-6-1.webp"
              },
              {
                "name": "Spaghetti with Meat Sauce** (Serves 4 – 6)",
                "calories": "2,840",
                "price": "48.99",
                "image_url": "/static/image/upload/Spaghetti-with-Meat-Sauce-Serves-4-–-6-1.webp"
              },
              {
                "name": "Spaghetti with Marinara Sauce (Serves 4 – 6)",
                "calories": "2,270",
                "price": "48.99",
                "image_url": "/static/image/upload/Spaghetti-with-Marinara-Sauce-Serves-4-6-1.webp"
              },
              {
                "name": "Chicken Tortelloni Alfredo (serves 4 – 6 )",
                "calories": "7,930",
                "price": "71.39",
                "image_url": "/static/image/upload/Chicken-Tortelloni-Alfredo-serves-4-6-1-1.webp"
              },
              {
                "name": "Lasagna Classico (Serves up to 6)",
                "calories": "3,420",
                "price": "52.99",
                "image_url": "/static/image/upload/Lasagna-Classico-Serves-up-to-6-1.webp"
              },
              {
                "name": "Lasagna Classico (Serves up to 12)",
                "calories": "6,470",
                "price": "62.99",
                "image_url": "/static/image/upload/Lasagna-Classico-Serves-up-to-12.webp",
                "review": "Be the hero of your next party! This giant pan of Lasagna Classico will have everyone cheering. It's the easiest way to bring the Olive Garden experience home. 🎉"
              },
              {
                "name": "Chicken Scampi (Serves 4 – 6)",
                "calories": "4,190",
                "price": "59.99",
                "image_url": "/static/image/upload/Chicken-Scampi-Serves-4-6-1.webp"
              },
              {
                "name": "Chicken and Shrimp Carbonara (Serves 4 – 6)",
                "calories": "5,460",
                "price": "72.79",
                "image_url": "/static/image/upload/Chicken-and-Shrimp-Carbonara-Serves-4-6-1.webp"
              },
              {
                "name": "Shrimp Scampi (Serves 4 – 6)",
                "calories": "1,980",
                "price": "70.79",
                "image_url": "/static/image/upload/Shrimp-Scampi-Serves-4-6-1.webp"
              },
              {
                "name": "Cheese Ravioli with Marinara or Meat Sauce (Serves 4 – 6)",
                "calories": "3,510",
                "price": "52.99",
                "image_url": "/static/image/upload/Cheese-Ravioli-with-Marinara-or-Meat-Sauce-Serves-4-6.webp"
              }
            ]
          }
        }
      }
    },
    {
      "type": "faq",
      "data": {
        "title": "Your Catering Questions, Answered! 🤔",
        "items": [
          {
            "question": "What comes with an Olive Garden catering order?",
            "answer": "Everything you need! Every order comes with grated cheese, all the utensils, table covers, plates, napkins, and even those little after-dinner mints. You can also ask for chafing dishes to keep things warm! 🔥"
          },
          {
            "question": "How far in advance do I need to order catering?",
            "answer": "Just give them a heads-up by 5 p.m. for next-day lunch delivery! But you can also be a super-planner and schedule your order way in advance. They love that!"
          },
          {
            "question": "Is there a minimum order for catering delivery?",
            "answer": "Yep, there's a $100 minimum order to get it delivered. That's before taxes and the delivery fee. Easy to hit when you're ordering pans of deliciousness!"
          }
        ]
      }
    }
  ]
}
