{
  "metadata": {
    "h1": "The Official Olive Garden Pasta Menu 2025? Every Price!",
    "description": "Craving carbs? Check out the full Olive Garden Pasta Menu for 2025, with prices for every dish from Alfredo to Ziti. Let's get saucy!",
    "coreKeyword": "Olive Garden Pasta Menu",
    "author": {
      "name": "The Olive Garden Menu Guide Team",
      "email": "contact@olivegardenmenuguide.com"
    },
    "datePublished": "2025-10-19"
  },
  "contentBlocks": [
    {
      "type": "richText",
      "data": {
        "htmlContent": "<p>Let's be real, you go to Olive Garden for the PASTA. 🍝 It's the ultimate comfort food, and their menu is a playground of creamy, cheesy, saucy goodness. Whether you're a fan of the classics or want to build your own masterpiece, the pasta possibilities are endless. Let's dive in! ✨</p>"
      }
    },
    {
      "type": "dataTable",
      "data": {
        "title": "Olive Garden Pasta Menu & Prices (September 2025)",
        "categoriesDataUrl": "raw/index-full-menu.json",
        "categoriesFilter": [
          "Classic Entrées",
          "Amazing Alfredos!",
          "Create Your Own Pasta"
        ]
      }
    },
    {
      "type": "faq",
      "data": {
        "title": "Your Pasta Questions, Answered! 🍝",
        "items": [
          {
            "question": "Can I really create my own pasta at Olive Garden?",
            "answer": "YES! The 'Create Your Own Pasta' option is the ultimate game-changer. You pick the pasta, the sauce, and the toppings. Go wild!"
          },
          {
            "question": "Are there gluten-free pasta options?",
            "answer": "You bet! Olive Garden offers gluten-free rotini pasta. Just let your server know, and they'll hook you up with a delicious gluten-sensitive meal."
          },
          {
            "question": "Do pasta dishes come with breadsticks and salad?",
            "answer": "Of course! It wouldn't be Olive Garden without unlimited breadsticks and your choice of their famous house salad or a soup. It's all included with your entrée. 🙌"
          }
        ]
      }
    }
  ]
}
